{
	"c": "Shape",
	"p": {
		"name": "shape",
		"x": 532,
		"y": 418,
		"shape": 4,
		"shapeFillColor": 2241348,
		"_shapePoints": [
			{
				"x": -12,
				"y": -33
			},
			{
				"x": 34,
				"y": -41
			},
			{
				"x": 71,
				"y": 2
			},
			{
				"x": 37,
				"y": 8
			},
			{
				"x": 41,
				"y": 45
			},
			{
				"x": -9,
				"y": 47
			},
			{
				"x": -16,
				"y": 11
			},
			{
				"x": -48,
				"y": 13
			}
		]
	},
	":": [
		{
			"c": "Shape",
			"p": {
				"name": "shape",
				"x": 13,
				"y": 9,
				"shape": 4,
				"shapeFillColor": 4478310,
				"_shapePoints": [
					{
						"x": -17,
						"y": -37
					},
					{
						"x": 10,
						"y": -40
					},
					{
						"x": 43,
						"y": -11
					},
					{
						"x": 11,
						"y": -7
					},
					{
						"x": 11,
						"y": 29
					},
					{
						"x": -16,
						"y": 30
					},
					{
						"x": -20,
						"y": -8
					},
					{
						"x": -46,
						"y": -6
					}
				]
			}
		},
		{
			"c": "Shape",
			"p": {
				"name": "shape",
				"x": 12,
				"y": -12,
				"shape": 4,
				"shapeFillColor": 7833753,
				"_shapePoints": [
					{
						"x": -8,
						"y": -10
					},
					{
						"x": 5,
						"y": -12
					},
					{
						"x": 30,
						"y": 5
					},
					{
						"x": 5,
						"y": 6
					},
					{
						"x": 6,
						"y": 31
					},
					{
						"x": -12,
						"y": 30
					},
					{
						"x": -13,
						"y": 7
					},
					{
						"x": -30,
						"y": 9
					}
				]
			}
		}
	]
}